pyslip/__init__.py
pyslip/blue_marble.py
pyslip/gmt_local.py
pyslip/log.py
pyslip/mapquest.py
pyslip/modest_maps.py
pyslip/open_street_map.py
pyslip/pycacheback.py
pyslip/pyslip.py
pyslip/stamen_toner.py
pyslip/stamen_transport.py
pyslip/stamen_watercolor.py
pyslip/sys_tile_data.py
pyslip/tiles.py
pyslip/tiles_net.py
pyslip/tkinter_error.py
pyslip/examples/README.rst
pyslip/examples/appstaticbox.py
pyslip/examples/gmt_local_tiles.tar.gz
pyslip/examples/gmt_local_tiles.zip
pyslip/examples/layer_control.py
pyslip/examples/pyslip_demo.py
pyslip/examples/rotextctrl.py
pyslip/examples/test_assumptions.py
pyslip/examples/test_displayable_levels.py
pyslip/examples/test_gmt_local_tiles.py
pyslip/examples/test_gotoposition.py
pyslip/examples/test_image_placement.py
pyslip/examples/test_maprel_image.py
pyslip/examples/test_maprel_polygon.py
pyslip/examples/test_maprel_text.py
pyslip/examples/test_multi_widget.py
pyslip/examples/test_osm_tiles.py
pyslip/examples/test_point_placement.py
pyslip/examples/test_polygon_placement.py
pyslip/examples/test_polyline_placement.py
pyslip/examples/test_text_placement.py
pyslip/examples/test_viewrel_image.py
pyslip/examples/test_viewrel_point.py
pyslip/examples/test_viewrel_polygon.py
pyslip/examples/test_viewrel_text.py
pyslip/examples/graphics/arrow_down.png
pyslip/examples/graphics/arrow_left.png
pyslip/examples/graphics/arrow_leftdown.png
pyslip/examples/graphics/arrow_leftup.png
pyslip/examples/graphics/arrow_right.png
pyslip/examples/graphics/arrow_rightdown.png
pyslip/examples/graphics/arrow_rightup.png
pyslip/examples/graphics/arrow_up.png
pyslip/examples/graphics/compass_rose.png
pyslip/examples/graphics/error_tile.png
pyslip/examples/graphics/glassy_button_2.png
pyslip/examples/graphics/glassy_button_3.png
pyslip/examples/graphics/glassy_button_4.png
pyslip/examples/graphics/glassy_button_5.png
pyslip/examples/graphics/glassy_button_6.png
pyslip/examples/graphics/grid.jpg
pyslip/examples/graphics/grid.png
pyslip-4.0.5.dist-info/LICENSE
pyslip-4.0.5.dist-info/METADATA
pyslip-4.0.5.dist-info/WHEEL
pyslip-4.0.5.dist-info/top_level.txt
pyslip-4.0.5.dist-info/RECORD
