Metadata-Version: 2.1
Name: pyslip
Version: 4.0.5
Summary: A slipmap widget for wxPython 4
Home-page: http://github.com/rzzzwilson/pySlip
Author: Ross Wilson
Author-email: rzzzwilson@gmail.com
License: MIT
Download-URL: https://github.com/rzzzwilson/pySlip/releases/tag/4.0.5
Keywords: python wxpython slipmap map
Platform: UNKNOWN
Classifier: Development Status :: 4 - Beta
Classifier: Intended Audience :: Developers
Classifier: License :: OSI Approved :: MIT License
Classifier: Operating System :: OS Independent
Classifier: Programming Language :: Python :: 3
Requires-Dist: wxpython
